Assignment-1/ADD/add_1bit.v
`timescale 1ns / 1ps

module add_1bit(
  input a,
  input b,
  input cin,
  output sum,
  output co);

  xor g1(sum, a, b, cin);
  and g2(k, a, b);
  and g3(l, a, cin);
  and g4(m, b, cin);
  or g5(co, k, l, m);

endmodule

Assignment-1/Sub/add_64bit.v
`timescale 1ns/1ps
module add_64bit(a, b, out, overflow);	

	input signed [63:0]a ;
	input signed [63:0]b ;
	output signed [63:0]out ;
	output overflow;

	wire [64:0]carry;

	assign carry[0] = 1'b0;

	genvar i;

	generate for(i = 0; i < 64; i = i+1) 
  	begin
    		add_1bit g1(a[i], b[i], carry[i], out[i], carry[i+1]);
  	end
  	endgenerate

	xor g2(overflow, carry[64], carry[63]);

endmodule

Assignment-1/ADD/add_64bittb.v
`timescale 1ns/1ps


module add_64bittb;

	reg signed [63:0]a;
	reg signed [63:0]b;

	wire signed [63:0]out;
	wire  overflow;
	add_64bit dut(.a(a), .b(b), .out(out), .overflow(overflow));

	initial begin
		$dumpfile("add_64bit.vcd");
		$dumpvars(0, add_64bittb);

		a=64'b0000000000000000000000000000000000000000000000000000000000000000;
		b=64'b0000000000000000000000000000000000000000000000000000000000000000;

	repeat(8) begin 
		#10 begin
			a = ~a;
			a = a<<4;
			a = ~a;
		end
		#20 begin
			b = ~b;
			b = b<<8;
			b = ~b;
		end
	end
	repeat(4) begin 
		#10 begin
			a = ~a;
			a = a<<8;
			a = ~a;
		end
		#20 b= b<<16;
	
		
	end
	end

  initial 
		$monitor("a=%d b=%d out=%d overflow=%b\n",a, b, out, overflow);

endmodule

Assignment-1/ADD/add_64bit.vcd
$date
	Sat Jan 29 05:18:40 2022
$end
$version
	Icarus Verilog
$end
$timescale
	1ps
$end
$scope module add_64bittb $end
$var wire 1 ! overflow $end
$var wire 64 " out [63:0] $end
$var reg 64 # a [63:0] $end
$var reg 64 $ b [63:0] $end
$scope module dut $end
$var wire 64 % a [63:0] $end
$var wire 64 & b [63:0] $end
$var wire 1 ! overflow $end
$var wire 64 ' out [63:0] $end
$var wire 65 ( carry [64:0] $end
$scope begin genblk1[0] $end
$scope module g1 $end
$var wire 1 ) a $end
$var wire 1 * b $end
$var wire 1 + cin $end
$var wire 1 , co $end
$var wire 1 - k $end
$var wire 1 . l $end
$var wire 1 / m $end
$var wire 1 0 sum $end
$upscope $end
$upscope $end
$scope begin genblk1[1] $end
$scope module g1 $end
$var wire 1 1 a $end
$var wire 1 2 b $end
$var wire 1 3 cin $end
$var wire 1 4 co $end
$var wire 1 5 k $end
$var wire 1 6 l $end
$var wire 1 7 m $end
$var wire 1 8 sum $end
$upscope $end
$upscope $end
$scope begin genblk1[2] $end
$scope module g1 $end
$var wire 1 9 a $end
$var wire 1 : b $end
$var wire 1 ; cin $end
$var wire 1 < co $end
$var wire 1 = k $end
$var wire 1 > l $end
$var wire 1 ? m $end
$var wire 1 @ sum $end
$upscope $end
$upscope $end
$scope begin genblk1[3] $end
$scope module g1 $end
$var wire 1 A a $end
$var wire 1 B b $end
$var wire 1 C cin $end
$var wire 1 D co $end
$var wire 1 E k $end
$var wire 1 F l $end
$var wire 1 G m $end
$var wire 1 H sum $end
$upscope $end
$upscope $end
$scope begin genblk1[4] $end
$scope module g1 $end
$var wire 1 I a $end
$var wire 1 J b $end
$var wire 1 K cin $end
$var wire 1 L co $end
$var wire 1 M k $end
$var wire 1 N l $end
$var wire 1 O m $end
$var wire 1 P sum $end
$upscope $end
$upscope $end
$scope begin genblk1[5] $end
$scope module g1 $end
$var wire 1 Q a $end
$var wire 1 R b $end
$var wire 1 S cin $end
$var wire 1 T co $end
$var wire 1 U k $end
$var wire 1 V l $end
$var wire 1 W m $end
$var wire 1 X sum $end
$upscope $end
$upscope $end
$scope begin genblk1[6] $end
$scope module g1 $end
$var wire 1 Y a $end
$var wire 1 Z b $end
$var wire 1 [ cin $end
$var wire 1 \ co $end
$var wire 1 ] k $end
$var wire 1 ^ l $end
$var wire 1 _ m $end
$var wire 1 ` sum $end
$upscope $end
$upscope $end
$scope begin genblk1[7] $end
$scope module g1 $end
$var wire 1 a a $end
$var wire 1 b b $end
$var wire 1 c cin $end
$var wire 1 d co $end
$var wire 1 e k $end
$var wire 1 f l $end
$var wire 1 g m $end
$var wire 1 h sum $end
$upscope $end
$upscope $end
$scope begin genblk1[8] $end
$scope module g1 $end
$var wire 1 i a $end
$var wire 1 j b $end
$var wire 1 k cin $end
$var wire 1 l co $end
$var wire 1 m k $end
$var wire 1 n l $end
$var wire 1 o m $end
$var wire 1 p sum $end
$upscope $end
$upscope $end
$scope begin genblk1[9] $end
$scope module g1 $end
$var wire 1 q a $end
$var wire 1 r b $end
$var wire 1 s cin $end
$var wire 1 t co $end
$var wire 1 u k $end
$var wire 1 v l $end
$var wire 1 w m $end
$var wire 1 x sum $end
$upscope $end
$upscope $end
$scope begin genblk1[10] $end
$scope module g1 $end
$var wire 1 y a $end
$var wire 1 z b $end
$var wire 1 { cin $end
$var wire 1 | co $end
$var wire 1 } k $end
$var wire 1 ~ l $end
$var wire 1 !" m $end
$var wire 1 "" sum $end
$upscope $end
$upscope $end
$scope begin genblk1[11] $end
$scope module g1 $end
$var wire 1 #" a $end
$var wire 1 $" b $end
$var wire 1 %" cin $end
$var wire 1 &" co $end
$var wire 1 '" k $end
$var wire 1 (" l $end
$var wire 1 )" m $end
$var wire 1 *" sum $end
$upscope $end
$upscope $end
$scope begin genblk1[12] $end
$scope module g1 $end
$var wire 1 +" a $end
$var wire 1 ," b $end
$var wire 1 -" cin $end
$var wire 1 ." co $end
$var wire 1 /" k $end
$var wire 1 0" l $end
$var wire 1 1" m $end
$var wire 1 2" sum $end
$upscope $end
$upscope $end
$scope begin genblk1[13] $end
$scope module g1 $end
$var wire 1 3" a $end
$var wire 1 4" b $end
$var wire 1 5" cin $end
$var wire 1 6" co $end
$var wire 1 7" k $end
$var wire 1 8" l $end
$var wire 1 9" m $end
$var wire 1 :" sum $end
$upscope $end
$upscope $end
$scope begin genblk1[14] $end
$scope module g1 $end
$var wire 1 ;" a $end
$var wire 1 <" b $end
$var wire 1 =" cin $end
$var wire 1 >" co $end
$var wire 1 ?" k $end
$var wire 1 @" l $end
$var wire 1 A" m $end
$var wire 1 B" sum $end
$upscope $end
$upscope $end
$scope begin genblk1[15] $end
$scope module g1 $end
$var wire 1 C" a $end
$var wire 1 D" b $end
$var wire 1 E" cin $end
$var wire 1 F" co $end
$var wire 1 G" k $end
$var wire 1 H" l $end
$var wire 1 I" m $end
$var wire 1 J" sum $end
$upscope $end
$upscope $end
$scope begin genblk1[16] $end
$scope module g1 $end
$var wire 1 K" a $end
$var wire 1 L" b $end
$var wire 1 M" cin $end
$var wire 1 N" co $end
$var wire 1 O" k $end
$var wire 1 P" l $end
$var wire 1 Q" m $end
$var wire 1 R" sum $end
$upscope $end
$upscope $end
$scope begin genblk1[17] $end
$scope module g1 $end
$var wire 1 S" a $end
$var wire 1 T" b $end
$var wire 1 U" cin $end
$var wire 1 V" co $end
$var wire 1 W" k $end
$var wire 1 X" l $end
$var wire 1 Y" m $end
$var wire 1 Z" sum $end
$upscope $end
$upscope $end
$scope begin genblk1[18] $end
$scope module g1 $end
$var wire 1 [" a $end
$var wire 1 \" b $end
$var wire 1 ]" cin $end
$var wire 1 ^" co $end
$var wire 1 _" k $end
$var wire 1 `" l $end
$var wire 1 a" m $end
$var wire 1 b" sum $end
$upscope $end
$upscope $end
$scope begin genblk1[19] $end
$scope module g1 $end
$var wire 1 c" a $end
$var wire 1 d" b $end
$var wire 1 e" cin $end
$var wire 1 f" co $end
$var wire 1 g" k $end
$var wire 1 h" l $end
$var wire 1 i" m $end
$var wire 1 j" sum $end
$upscope $end
$upscope $end
$scope begin genblk1[20] $end
$scope module g1 $end
$var wire 1 k" a $end
$var wire 1 l" b $end
$var wire 1 m" cin $end
$var wire 1 n" co $end
$var wire 1 o" k $end
$var wire 1 p" l $end
$var wire 1 q" m $end
$var wire 1 r" sum $end
$upscope $end
$upscope $end
$scope begin genblk1[21] $end
$scope module g1 $end
$var wire 1 s" a $end
$var wire 1 t" b $end
$var wire 1 u" cin $end
$var wire 1 v" co $end
$var wire 1 w" k $end
$var wire 1 x" l $end
$var wire 1 y" m $end
$var wire 1 z" sum $end
$upscope $end
$upscope $end
$scope begin genblk1[22] $end
$scope module g1 $end
$var wire 1 {" a $end
$var wire 1 |" b $end
$var wire 1 }" cin $end
$var wire 1 ~" co $end
$var wire 1 !# k $end
$var wire 1 "# l $end
$var wire 1 ## m $end
$var wire 1 $# sum $end
$upscope $end
$upscope $end
$scope begin genblk1[23] $end
$scope module g1 $end
$var wire 1 %# a $end
$var wire 1 &# b $end
$var wire 1 '# cin $end
$var wire 1 (# co $end
$var wire 1 )# k $end
$var wire 1 *# l $end
$var wire 1 +# m $end
$var wire 1 ,# sum $end
$upscope $end
$upscope $end
$scope begin genblk1[24] $end
$scope module g1 $end
$var wire 1 -# a $end
$var wire 1 .# b $end
$var wire 1 /# cin $end
$var wire 1 0# co $end
$var wire 1 1# k $end
$var wire 1 2# l $end
$var wire 1 3# m $end
$var wire 1 4# sum $end
$upscope $end
$upscope $end
$scope begin genblk1[25] $end
$scope module g1 $end
$var wire 1 5# a $end
$var wire 1 6# b $end
$var wire 1 7# cin $end
$var wire 1 8# co $end
$var wire 1 9# k $end
$var wire 1 :# l $end
$var wire 1 ;# m $end
$var wire 1 <# sum $end
$upscope $end
$upscope $end
$scope begin genblk1[26] $end
$scope module g1 $end
$var wire 1 =# a $end
$var wire 1 ># b $end
$var wire 1 ?# cin $end
$var wire 1 @# co $end
$var wire 1 A# k $end
$var wire 1 B# l $end
$var wire 1 C# m $end
$var wire 1 D# sum $end
$upscope $end
$upscope $end
$scope begin genblk1[27] $end
$scope module g1 $end
$var wire 1 E# a $end
$var wire 1 F# b $end
$var wire 1 G# cin $end
$var wire 1 H# co $end
$var wire 1 I# k $end
$var wire 1 J# l $end
$var wire 1 K# m $end
$var wire 1 L# sum $end
$upscope $end
$upscope $end
$scope begin genblk1[28] $end
$scope module g1 $end
$var wire 1 M# a $end
$var wire 1 N# b $end
$var wire 1 O# cin $end
$var wire 1 P# co $end
$var wire 1 Q# k $end
$var wire 1 R# l $end
$var wire 1 S# m $end
$var wire 1 T# sum $end
$upscope $end
$upscope $end
$scope begin genblk1[29] $end
$scope module g1 $end
$var wire 1 U# a $end
$var wire 1 V# b $end
$var wire 1 W# cin $end
$var wire 1 X# co $end
$var wire 1 Y# k $end
$var wire 1 Z# l $end
$var wire 1 [# m $end
$var wire 1 \# sum $end
$upscope $end
$upscope $end
$scope begin genblk1[30] $end
$scope module g1 $end
$var wire 1 ]# a $end
$var wire 1 ^# b $end
$var wire 1 _# cin $end
$var wire 1 `# co $end
$var wire 1 a# k $end
$var wire 1 b# l $end
$var wire 1 c# m $end
$var wire 1 d# sum $end
$upscope $end
$upscope $end
$scope begin genblk1[31] $end
$scope module g1 $end
$var wire 1 e# a $end
$var wire 1 f# b $end
$var wire 1 g# cin $end
$var wire 1 h# co $end
$var wire 1 i# k $end
$var wire 1 j# l $end
$var wire 1 k# m $end
$var wire 1 l# sum $end
$upscope $end
$upscope $end
$scope begin genblk1[32] $end
$scope module g1 $end
$var wire 1 m# a $end
$var wire 1 n# b $end
$var wire 1 o# cin $end
$var wire 1 p# co $end
$var wire 1 q# k $end
$var wire 1 r# l $end
$var wire 1 s# m $end
$var wire 1 t# sum $end
$upscope $end
$upscope $end
$scope begin genblk1[33] $end
$scope module g1 $end
$var wire 1 u# a $end
$var wire 1 v# b $end
$var wire 1 w# cin $end
$var wire 1 x# co $end
$var wire 1 y# k $end
$var wire 1 z# l $end
$var wire 1 {# m $end
$var wire 1 |# sum $end
$upscope $end
$upscope $end
$scope begin genblk1[34] $end
$scope module g1 $end
$var wire 1 }# a $end
$var wire 1 ~# b $end
$var wire 1 !$ cin $end
$var wire 1 "$ co $end
$var wire 1 #$ k $end
$var wire 1 $$ l $end
$var wire 1 %$ m $end
$var wire 1 &$ sum $end
$upscope $end
$upscope $end
$scope begin genblk1[35] $end
$scope module g1 $end
$var wire 1 '$ a $end
$var wire 1 ($ b $end
$var wire 1 )$ cin $end
$var wire 1 *$ co $end
$var wire 1 +$ k $end
$var wire 1 ,$ l $end
$var wire 1 -$ m $end
$var wire 1 .$ sum $end
$upscope $end
$upscope $end
$scope begin genblk1[36] $end
$scope module g1 $end
$var wire 1 /$ a $end
$var wire 1 0$ b $end
$var wire 1 1$ cin $end
$var wire 1 2$ co $end
$var wire 1 3$ k $end
$var wire 1 4$ l $end
$var wire 1 5$ m $end
$var wire 1 6$ sum $end
$upscope $end
$upscope $end
$scope begin genblk1[37] $end
$scope module g1 $end
$var wire 1 7$ a $end
$var wire 1 8$ b $end
$var wire 1 9$ cin $end
$var wire 1 :$ co $end
$var wire 1 ;$ k $end
$var wire 1 <$ l $end
$var wire 1 =$ m $end
$var wire 1 >$ sum $end
$upscope $end
$upscope $end
$scope begin genblk1[38] $end
$scope module g1 $end
$var wire 1 ?$ a $end
$var wire 1 @$ b $end
$var wire 1 A$ cin $end
$var wire 1 B$ co $end
$var wire 1 C$ k $end
$var wire 1 D$ l $end
$var wire 1 E$ m $end
$var wire 1 F$ sum $end
$upscope $end
$upscope $end
$scope begin genblk1[39] $end
$scope module g1 $end
$var wire 1 G$ a $end
$var wire 1 H$ b $end
$var wire 1 I$ cin $end
$var wire 1 J$ co $end
$var wire 1 K$ k $end
$var wire 1 L$ l $end
$var wire 1 M$ m $end
$var wire 1 N$ sum $end
$upscope $end
$upscope $end
$scope begin genblk1[40] $end
$scope module g1 $end
$var wire 1 O$ a $end
$var wire 1 P$ b $end
$var wire 1 Q$ cin $end
$var wire 1 R$ co $end
$var wire 1 S$ k $end
$var wire 1 T$ l $end
$var wire 1 U$ m $end
$var wire 1 V$ sum $end
$upscope $end
$upscope $end
$scope begin genblk1[41] $end
$scope module g1 $end
$var wire 1 W$ a $end
$var wire 1 X$ b $end
$var wire 1 Y$ cin $end
$var wire 1 Z$ co $end
$var wire 1 [$ k $end
$var wire 1 \$ l $end
$var wire 1 ]$ m $end
$var wire 1 ^$ sum $end
$upscope $end
$upscope $end
$scope begin genblk1[42] $end
$scope module g1 $end
$var wire 1 _$ a $end
$var wire 1 `$ b $end
$var wire 1 a$ cin $end
$var wire 1 b$ co $end
$var wire 1 c$ k $end
$var wire 1 d$ l $end
$var wire 1 e$ m $end
$var wire 1 f$ sum $end
$upscope $end
$upscope $end
$scope begin genblk1[43] $end
$scope module g1 $end
$var wire 1 g$ a $end
$var wire 1 h$ b $end
$var wire 1 i$ cin $end
$var wire 1 j$ co $end
$var wire 1 k$ k $end
$var wire 1 l$ l $end
$var wire 1 m$ m $end
$var wire 1 n$ sum $end
$upscope $end
$upscope $end
$scope begin genblk1[44] $end
$scope module g1 $end
$var wire 1 o$ a $end
$var wire 1 p$ b $end
$var wire 1 q$ cin $end
$var wire 1 r$ co $end
$var wire 1 s$ k $end
$var wire 1 t$ l $end
$var wire 1 u$ m $end
$var wire 1 v$ sum $end
$upscope $end
$upscope $end
$scope begin genblk1[45] $end
$scope module g1 $end
$var wire 1 w$ a $end
$var wire 1 x$ b $end
$var wire 1 y$ cin $end
$var wire 1 z$ co $end
$var wire 1 {$ k $end
$var wire 1 |$ l $end
$var wire 1 }$ m $end
$var wire 1 ~$ sum $end
$upscope $end
$upscope $end
$scope begin genblk1[46] $end
$scope module g1 $end
$var wire 1 !% a $end
$var wire 1 "% b $end
$var wire 1 #% cin $end
$var wire 1 $% co $end
$var wire 1 %% k $end
$var wire 1 &% l $end
$var wire 1 '% m $end
$var wire 1 (% sum $end
$upscope $end
$upscope $end
$scope begin genblk1[47] $end
$scope module g1 $end
$var wire 1 )% a $end
$var wire 1 *% b $end
$var wire 1 +% cin $end
$var wire 1 ,% co $end
$var wire 1 -% k $end
$var wire 1 .% l $end
$var wire 1 /% m $end
$var wire 1 0% sum $end
$upscope $end
$upscope $end
$scope begin genblk1[48] $end
$scope module g1 $end
$var wire 1 1% a $end
$var wire 1 2% b $end
$var wire 1 3% cin $end
$var wire 1 4% co $end
$var wire 1 5% k $end
$var wire 1 6% l $end
$var wire 1 7% m $end
$var wire 1 8% sum $end
$upscope $end
$upscope $end
$scope begin genblk1[49] $end
$scope module g1 $end
$var wire 1 9% a $end
$var wire 1 :% b $end
$var wire 1 ;% cin $end
$var wire 1 <% co $end
$var wire 1 =% k $end
$var wire 1 >% l $end
$var wire 1 ?% m $end
$var wire 1 @% sum $end
$upscope $end
$upscope $end
$scope begin genblk1[50] $end
$scope module g1 $end
$var wire 1 A% a $end
$var wire 1 B% b $end
$var wire 1 C% cin $end
$var wire 1 D% co $end
$var wire 1 E% k $end
$var wire 1 F% l $end
$var wire 1 G% m $end
$var wire 1 H% sum $end
$upscope $end
$upscope $end
$scope begin genblk1[51] $end
$scope module g1 $end
$var wire 1 I% a $end
$var wire 1 J% b $end
$var wire 1 K% cin $end
$var wire 1 L% co $end
$var wire 1 M% k $end
$var wire 1 N% l $end
$var wire 1 O% m $end
$var wire 1 P% sum $end
$upscope $end
$upscope $end
$scope begin genblk1[52] $end
$scope module g1 $end
$var wire 1 Q% a $end
$var wire 1 R% b $end
$var wire 1 S% cin $end
$var wire 1 T% co $end
$var wire 1 U% k $end
$var wire 1 V% l $end
$var wire 1 W% m $end
$var wire 1 X% sum $end
$upscope $end
$upscope $end
$scope begin genblk1[53] $end
$scope module g1 $end
$var wire 1 Y% a $end
$var wire 1 Z% b $end
$var wire 1 [% cin $end
$var wire 1 \% co $end
$var wire 1 ]% k $end
$var wire 1 ^% l $end
$var wire 1 _% m $end
$var wire 1 `% sum $end
$upscope $end
$upscope $end
$scope begin genblk1[54] $end
$scope module g1 $end
$var wire 1 a% a $end
$var wire 1 b% b $end
$var wire 1 c% cin $end
$var wire 1 d% co $end
$var wire 1 e% k $end
$var wire 1 f% l $end
$var wire 1 g% m $end
$var wire 1 h% sum $end
$upscope $end
$upscope $end
$scope begin genblk1[55] $end
$scope module g1 $end
$var wire 1 i% a $end
$var wire 1 j% b $end
$var wire 1 k% cin $end
$var wire 1 l% co $end
$var wire 1 m% k $end
$var wire 1 n% l $end
$var wire 1 o% m $end
$var wire 1 p% sum $end
$upscope $end
$upscope $end
$scope begin genblk1[56] $end
$scope module g1 $end
$var wire 1 q% a $end
$var wire 1 r% b $end
$var wire 1 s% cin $end
$var wire 1 t% co $end
$var wire 1 u% k $end
$var wire 1 v% l $end
$var wire 1 w% m $end
$var wire 1 x% sum $end
$upscope $end
$upscope $end
$scope begin genblk1[57] $end
$scope module g1 $end
$var wire 1 y% a $end
$var wire 1 z% b $end
$var wire 1 {% cin $end
$var wire 1 |% co $end
$var wire 1 }% k $end
$var wire 1 ~% l $end
$var wire 1 !& m $end
$var wire 1 "& sum $end
$upscope $end
$upscope $end
$scope begin genblk1[58] $end
$scope module g1 $end
$var wire 1 #& a $end
$var wire 1 $& b $end
$var wire 1 %& cin $end
$var wire 1 && co $end
$var wire 1 '& k $end
$var wire 1 (& l $end
$var wire 1 )& m $end
$var wire 1 *& sum $end
$upscope $end
$upscope $end
$scope begin genblk1[59] $end
$scope module g1 $end
$var wire 1 +& a $end
$var wire 1 ,& b $end
$var wire 1 -& cin $end
$var wire 1 .& co $end
$var wire 1 /& k $end
$var wire 1 0& l $end
$var wire 1 1& m $end
$var wire 1 2& sum $end
$upscope $end
$upscope $end
$scope begin genblk1[60] $end
$scope module g1 $end
$var wire 1 3& a $end
$var wire 1 4& b $end
$var wire 1 5& cin $end
$var wire 1 6& co $end
$var wire 1 7& k $end
$var wire 1 8& l $end
$var wire 1 9& m $end
$var wire 1 :& sum $end
$upscope $end
$upscope $end
$scope begin genblk1[61] $end
$scope module g1 $end
$var wire 1 ;& a $end
$var wire 1 <& b $end
$var wire 1 =& cin $end
$var wire 1 >& co $end
$var wire 1 ?& k $end
$var wire 1 @& l $end
$var wire 1 A& m $end
$var wire 1 B& sum $end
$upscope $end
$upscope $end
$scope begin genblk1[62] $end
$scope module g1 $end
$var wire 1 C& a $end
$var wire 1 D& b $end
$var wire 1 E& cin $end
$var wire 1 F& co $end
$var wire 1 G& k $end
$var wire 1 H& l $end
$var wire 1 I& m $end
$var wire 1 J& sum $end
$upscope $end
$upscope $end
$scope begin genblk1[63] $end
$scope module g1 $end
$var wire 1 K& a $end
$var wire 1 L& b $end
$var wire 1 M& cin $end
$var wire 1 N& co $end
$var wire 1 O& k $end
$var wire 1 P& l $end
$var wire 1 Q& m $end
$var wire 1 R& sum $end
$upscope $end
$upscope $end
$upscope $end
$upscope $end
$enddefinitions $end
#0
$dumpvars
0R&
0Q&
0P&
0O&
0N&
0M&
0L&
0K&
0J&
0I&
0H&
0G&
0F&
0E&
0D&
0C&
0B&
0A&
0@&
0?&
0>&
0=&
0<&
0;&
0:&
09&
08&
07&
06&
05&
04&
03&
02&
01&
00&
0/&
0.&
0-&
0,&
0+&
0*&
0)&
0(&
0'&
0&&
0%&
0$&
0#&
0"&
0!&
0~%
0}%
0|%
0{%
0z%
0y%
0x%
0w%
0v%
0u%
0t%
0s%
0r%
0q%
0p%
0o%
0n%
0m%
0l%
0k%
0j%
0i%
0h%
0g%
0f%
0e%
0d%
0c%
0b%
0a%
0`%
0_%
0^%
0]%
0\%
0[%
0Z%
0Y%
0X%
0W%
0V%
0U%
0T%
0S%
0R%
0Q%
0P%
0O%
0N%
0M%
0L%
0K%
0J%
0I%
0H%
0G%
0F%
0E%
0D%
0C%
0B%
0A%
0@%
0?%
0>%
0=%
0<%
0;%
0:%
09%
08%
07%
06%
05%
04%
03%
02%
01%
00%
0/%
0.%
0-%
0,%
0+%
0*%
0)%
0(%
0'%
0&%
0%%
0$%
0#%
0"%
0!%
0~$
0}$
0|$
0{$
0z$
0y$
0x$
0w$
0v$
0u$
0t$
0s$
0r$
0q$
0p$
0o$
0n$
0m$
0l$
0k$
0j$
0i$
0h$
0g$
0f$
0e$
0d$
0c$
0b$
0a$
0`$
0_$
0^$
0]$
0\$
0[$
0Z$
0Y$
0X$
0W$
0V$
0U$
0T$
0S$
0R$
0Q$
0P$
0O$
0N$
0M$
0L$
0K$
0J$
0I$
0H$
0G$
0F$
0E$
0D$
0C$
0B$
0A$
0@$
0?$
0>$
0=$
0<$
0;$
0:$
09$
08$
07$
06$
05$
04$
03$
02$
01$
00$
0/$
0.$
0-$
0,$
0+$
0*$
0)$
0($
0'$
0&$
0%$
0$$
0#$
0"$
0!$
0~#
0}#
0|#
0{#
0z#
0y#
0x#
0w#
0v#
0u#
0t#
0s#
0r#
0q#
0p#
0o#
0n#
0m#
0l#
0k#
0j#
0i#
0h#
0g#
0f#
0e#
0d#
0c#
0b#
0a#
0`#
0_#
0^#
0]#
0\#
0[#
0Z#
0Y#
0X#
0W#
0V#
0U#
0T#
0S#
0R#
0Q#
0P#
0O#
0N#
0M#
0L#
0K#
0J#
0I#
0H#
0G#
0F#
0E#
0D#
0C#
0B#
0A#
0@#
0?#
0>#
0=#
0<#
0;#
0:#
09#
08#
07#
06#
05#
04#
03#
02#
01#
00#
0/#
0.#
0-#
0,#
0+#
0*#
0)#
0(#
0'#
0&#
0%#
0$#
0##
0"#
0!#
0~"
0}"
0|"
0{"
0z"
0y"
0x"
0w"
0v"
0u"
0t"
0s"
0r"
0q"
0p"
0o"
0n"
0m"
0l"
0k"
0j"
0i"
0h"
0g"
0f"
0e"
0d"
0c"
0b"
0a"
0`"
0_"
0^"
0]"
0\"
0["
0Z"
0Y"
0X"
0W"
0V"
0U"
0T"
0S"
0R"
0Q"
0P"
0O"
0N"
0M"
0L"
0K"
0J"
0I"
0H"
0G"
0F"
0E"
0D"
0C"
0B"
0A"
0@"
0?"
0>"
0="
0<"
0;"
0:"
09"
08"
07"
06"
05"
04"
03"
02"
01"
00"
0/"
0."
0-"
0,"
0+"
0*"
0)"
0("
0'"
0&"
0%"
0$"
0#"
0""
0!"
0~
0}
0|
0{
0z
0y
0x
0w
0v
0u
0t
0s
0r
0q
0p
0o
0n
0m
0l
0k
0j
0i
0h
0g
0f
0e
0d
0c
0b
0a
0`
0_
0^
0]
0\
0[
0Z
0Y
0X
0W
0V
0U
0T
0S
0R
0Q
0P
0O
0N
0M
0L
0K
0J
0I
0H
0G
0F
0E
0D
0C
0B
0A
0@
0?
0>
0=
0<
0;
0:
09
08
07
06
05
04
03
02
01
00
0/
0.
0-
0,
0+
0*
0)
b0 (
b0 '
b0 &
b0 %
b0 $
b0 #
b0 "
0!
$end
#10000
10
18
1@
b1111 "
b1111 '
1H
1)
11
19
1A
b1111 #
b1111 %
#30000
1p
1k
1d
1g
1c
1\
1_
1[
1T
1W
1S
1L
16
17
1>
1?
1F
1G
1O
13
1;
1C
1K
1,
14
1<
b111111110 (
1D
00
1-
18
15
1@
1=
1H
1E
0P
0X
0`
b100001110 "
b100001110 '
0h
1*
12
1:
1B
1J
1R
1Z
1b
b11111111 $
b11111111 &
#40000
1P
1M
1N
1X
1U
1V
1`
1]
1^
b111111110 "
b111111110 '
1h
1e
1f
1I
1Q
1Y
1a
b11111111 #
b11111111 %
#60000
1R"
1M"
1F"
1I"
1E"
1>"
1A"
1="
16"
19"
15"
1."
11"
1-"
1&"
1)"
1%"
1|
1!"
1{
1t
1w
1s
b11111111111111110 (
1l
0p
1o
0x
0""
0*"
02"
0:"
0B"
b10000000011111110 "
b10000000011111110 '
0J"
1j
1r
1z
1$"
1,"
14"
1<"
1D"
b1111111111111111 $
b1111111111111111 &
#70000
1p
1m
1n
1x
1u
1v
1""
1}
1~
b10000111111111110 "
b10000111111111110 '
1*"
1'"
1("
1i
1q
1y
1#"
b111111111111 #
b111111111111 %
#90000
14#
1/#
1(#
1+#
1'#
1~"
1##
1}"
1v"
1y"
1u"
1n"
1q"
1m"
1f"
1i"
1e"
1^"
1a"
1]"
1V"
1Y"
1U"
b1111111111111111111111110 (
1N"
0R"
1Q"
0Z"
0b"
0j"
0r"
0z"
0$#
b1000000000000111111111110 "
b1000000000000111111111110 '
0,#
1L"
1T"
1\"
1d"
1l"
1t"
1|"
1&#
b111111111111111111111111 $
b111111111111111111111111 &
#100000
12"
1/"
10"
1:"
17"
18"
1B"
1?"
1@"
b1000000001111111111111110 "
b1000000001111111111111110 '
1J"
1G"
1H"
1+"
13"
1;"
1C"
b1111111111111111 #
b1111111111111111 %
#120000
1t#
1o#
1h#
1k#
1g#
1`#
1c#
1_#
1X#
1[#
1W#
1P#
1S#
1O#
1H#
1K#
1G#
1@#
1C#
1?#
18#
1;#
17#
b111111111111111111111111111111110 (
10#
04#
13#
0<#
0D#
0L#
0T#
0\#
0d#
b100000000000000001111111111111110 "
b100000000000000001111111111111110 '
0l#
1.#
16#
1>#
1F#
1N#
1V#
1^#
1f#
b11111111111111111111111111111111 $
b11111111111111111111111111111111 &
#130000
1R"
1O"
1P"
1Z"
1W"
1X"
1b"
1_"
1`"
b100000000000011111111111111111110 "
b100000000000011111111111111111110 '
1j"
1g"
1h"
1K"
1S"
1["
1c"
b11111111111111111111 #
b11111111111111111111 %
#150000
1V$
1Q$
1J$
1M$
1I$
1B$
1E$
1A$
1:$
1=$
19$
12$
15$
11$
1*$
1-$
1)$
1"$
1%$
1!$
1x#
1{#
1w#
b11111111111111111111111111111111111111110 (
1p#
0t#
1s#
0|#
0&$
0.$
06$
0>$
0F$
b10000000000000000000011111111111111111110 "
b10000000000000000000011111111111111111110 '
0N$
1n#
1v#
1~#
1($
10$
18$
1@$
1H$
b1111111111111111111111111111111111111111 $
b1111111111111111111111111111111111111111 &
#160000
1r"
1o"
1p"
1z"
1w"
1x"
1$#
1!#
1"#
b10000000000000000111111111111111111111110 "
b10000000000000000111111111111111111111110 '
1,#
1)#
1*#
1k"
1s"
1{"
1%#
b111111111111111111111111 #
b111111111111111111111111 %
#180000
18%
13%
1,%
1/%
1+%
1$%
1'%
1#%
1z$
1}$
1y$
1r$
1u$
1q$
1j$
1m$
1i$
1b$
1e$
1a$
1Z$
1]$
1Y$
b1111111111111111111111111111111111111111111111110 (
1R$
0V$
1U$
0^$
0f$
0n$
0v$
0~$
0(%
b1000000000000000000000000111111111111111111111110 "
b1000000000000000000000000111111111111111111111110 '
00%
1P$
1X$
1`$
1h$
1p$
1x$
1"%
1*%
b111111111111111111111111111111111111111111111111 $
b111111111111111111111111111111111111111111111111 &
#190000
14#
11#
12#
1<#
19#
1:#
1D#
1A#
1B#
b1000000000000000000001111111111111111111111111110 "
b1000000000000000000001111111111111111111111111110 '
1L#
1I#
1J#
1-#
15#
1=#
1E#
b1111111111111111111111111111 #
b1111111111111111111111111111 %
#210000
1x%
1s%
1l%
1o%
1k%
1d%
1g%
1c%
1\%
1_%
1[%
1T%
1W%
1S%
1L%
1O%
1K%
1D%
1G%
1C%
1<%
1?%
1;%
b111111111111111111111111111111111111111111111111111111110 (
14%
08%
17%
0@%
0H%
0P%
0X%
0`%
0h%
b100000000000000000000000000001111111111111111111111111110 "
b100000000000000000000000000001111111111111111111111111110 '
0p%
12%
1:%
1B%
1J%
1R%
1Z%
1b%
1j%
b11111111111111111111111111111111111111111111111111111111 $
b11111111111111111111111111111111111111111111111111111111 &
#220000
1T#
1Q#
1R#
1\#
1Y#
1Z#
1d#
1a#
1b#
b100000000000000000000000011111111111111111111111111111110 "
b100000000000000000000000011111111111111111111111111111110 '
1l#
1i#
1j#
1M#
1U#
1]#
1e#
b11111111111111111111111111111111 #
b11111111111111111111111111111111 %
