Y86-64 Processor/seq/memory/ram.v
`timescale 1ns / 1ps

module RAM(memaddr, memdata, read, write, valM, dmemerror);

input[63:0] memaddr;
input[63:0] memdata;
input read;
input write;

reg [63:0] memory[8191:0]; 

output reg[63:0] valM;
output reg dmemerror;


always @(write, read, memdata, memaddr) begin

	if(read && !write) begin
		valM <= memory[memaddr];
	end

	if(write && !read) begin
		memory[memaddr] <= memdata;
	end

	if (memaddr >= 64'd512) begin
		dmemerror <= 1'b1;
	end
	else begin
		dmemerror <= 1'b0;

	end

	
	
end


endmodule

module MEM_addr(icode, valE, valA, memaddr);

input[3:0] icode;
input [63:0] valE;
input[63:0] valA;

output reg[63:0] memaddr;

always @(icode, valE, valA) begin
	

	case (icode)
		4'h4, 4'h5, 4'hA, 4'h8: 
			memaddr <= valE;
		4'h9, 4'hB:
			memaddr <= valA;
	endcase

end

endmodule

module MEM_data(icode, valA, valP, memdata);

input[3:0] icode;
input [63:0] valA;
input[63:0] valP;

output reg[63:0] memdata;

always @(icode, valA, valP) begin
	
	case (icode)
		4'h4, 4'hA:
			memdata <= valA;
		4'h8:
			memdata<= valP;
		
	endcase
end

endmodule

module MEM_read (icode, read);

input [3:0] icode;
output reg read;

always @(icode) begin
	

	case (icode)
		4'h5, 4'hB, 4'h9:
			read <= 1'b1;
		default: read <= 1'b0;
	endcase
end
endmodule

module MEM_write (icode, write);

input [3:0] icode;
output reg write;

always @(icode) begin
	

	case (icode)
		4'h4, 4'hA, 4'h8:
			write <= 1'b1;
			
		default: write <= 1'b0;
	endcase
end
endmodule

module STAT(icode, instr_valid, imem_error, dmemerror, stat);
    input [3:0] icode;
    input imem_error;
    input instr_valid;
    input dmemerror;
    output reg[2:0] stat;

    parameter SAOK = 3'h1;
    parameter SHLT = 3'h2;
    parameter SADR = 3'h3;
    parameter SINS = 3'h4;

    always @(*)
    begin
        if(imem_error || dmemerror) 
            stat <= SADR;
        else if (!instr_valid)
            stat <= SINS;
        else if (icode == 4'h0)
            stat <= SHLT;
        else stat <= SAOK;
    end

endmodule

Y86-64 Processor/seq/memory/ram_tb.v
`timescale 1ns / 1ps

module ram_test;

    reg [3:0] icode;
    wire [63:0] memaddr;
    wire [63:0] memdata;
    reg [63:0] valE;
    reg [63:0] valA;
    reg [63:0] valP;
    wire [63:0] valM;
    wire read;
    wire write;

    RAM ram1(.memaddr(memaddr), .memdata(memdata), .read(read), .write(write), .valM(valM), .dmemerror(dmemerror));
    MEM_addr Ma(.icode(icode), .valA(valA), .valE(valE), .memaddr(memaddr));
    MEM_read Mr(.icode(icode), .read(read));
    MEM_write Mw(.icode(icode), .write(write));
    MEM_data Md(.icode(icode), .valA(valA), .valP(valP), .memdata(memdata));    

    
    integer k;
    parameter base_addr = 64'hFF;

    initial begin
    $dumpfile("ram_test.vcd");
    $dumpvars(0,ram_test);

    
    for(k=0;k<10;k++)
    begin
        icode <= 4'h4;
        valE  <= k + base_addr;
        valA  <= k+ $random;
        #10;
    end

    for(k=0;k<10;k++)
    begin
        icode <= 4'h5;
        valE  <= k + base_addr;
        #10;
    end

    #20 $finish;
        
    end

endmodule

Y86-64 Processor/seq/memory/ram_test.vcd
$date
	Thu Mar 10 01:43:28 2022
$end
$version
	Icarus Verilog
$end
$timescale
	1ps
$end
$scope module ram_test $end
$var wire 1 ! write $end
$var wire 64 " valM [63:0] $end
$var wire 1 # read $end
$var wire 64 $ memdata [63:0] $end
$var wire 64 % memaddr [63:0] $end
$var wire 1 & dmemerror $end
$var reg 4 ' icode [3:0] $end
$var reg 64 ( valA [63:0] $end
$var reg 64 ) valE [63:0] $end
$var reg 64 * valP [63:0] $end
$var integer 32 + k [31:0] $end
$scope module Ma $end
$var wire 4 , icode [3:0] $end
$var wire 64 - valA [63:0] $end
$var wire 64 . valE [63:0] $end
$var reg 64 / memaddr [63:0] $end
$upscope $end
$scope module Md $end
$var wire 4 0 icode [3:0] $end
$var wire 64 1 valA [63:0] $end
$var wire 64 2 valP [63:0] $end
$var reg 64 3 memdata [63:0] $end
$upscope $end
$scope module Mr $end
$var wire 4 4 icode [3:0] $end
$var reg 1 # read $end
$upscope $end
$scope module Mw $end
$var wire 4 5 icode [3:0] $end
$var reg 1 ! write $end
$upscope $end
$scope module ram1 $end
$var wire 64 6 memaddr [63:0] $end
$var wire 64 7 memdata [63:0] $end
$var wire 1 # read $end
$var wire 1 ! write $end
$var reg 1 & dmemerror $end
$var reg 64 8 valM [63:0] $end
$upscope $end
$upscope $end
$enddefinitions $end
#0
$dumpvars
bx 8
b10010000101010011010100100100 7
b11111111 6
b100 5
b100 4
b10010000101010011010100100100 3
bx 2
b10010000101010011010100100100 1
b100 0
b11111111 /
b11111111 .
b10010000101010011010100100100 -
b100 ,
b0 +
bx *
b11111111 )
b10010000101010011010100100100 (
b100 '
0&
b11111111 %
b10010000101010011010100100100 $
0#
bx "
1!
$end
#10000
b1111111111111111111111111111111111000000100010010101111010000010 $
b1111111111111111111111111111111111000000100010010101111010000010 3
b1111111111111111111111111111111111000000100010010101111010000010 7
b100000000 %
b100000000 /
b100000000 6
b1111111111111111111111111111111111000000100010010101111010000010 (
b1111111111111111111111111111111111000000100010010101111010000010 -
b1111111111111111111111111111111111000000100010010101111010000010 1
b100000000 )
b100000000 .
b1 +
#20000
b1111111111111111111111111111111110000100100001001101011000001011 $
b1111111111111111111111111111111110000100100001001101011000001011 3
b1111111111111111111111111111111110000100100001001101011000001011 7
b100000001 %
b100000001 /
b100000001 6
b1111111111111111111111111111111110000100100001001101011000001011 (
b1111111111111111111111111111111110000100100001001101011000001011 -
b1111111111111111111111111111111110000100100001001101011000001011 1
b100000001 )
b100000001 .
b10 +
#30000
b1111111111111111111111111111111110110001111100000101011001100110 $
b1111111111111111111111111111111110110001111100000101011001100110 3
b1111111111111111111111111111111110110001111100000101011001100110 7
b100000010 %
b100000010 /
b100000010 6
b1111111111111111111111111111111110110001111100000101011001100110 (
b1111111111111111111111111111111110110001111100000101011001100110 -
b1111111111111111111111111111111110110001111100000101011001100110 1
b100000010 )
b100000010 .
b11 +
#40000
b110101110010111101100010001 $
b110101110010111101100010001 3
b110101110010111101100010001 7
b100000011 %
b100000011 /
b100000011 6
b110101110010111101100010001 (
b110101110010111101100010001 -
b110101110010111101100010001 1
b100000011 )
b100000011 .
b100 +
#50000
b1000110110111111001100110010010 $
b1000110110111111001100110010010 3
b1000110110111111001100110010010 7
b100000100 %
b100000100 /
b100000100 6
b1000110110111111001100110010010 (
b1000110110111111001100110010010 -
b1000110110111111001100110010010 1
b100000100 )
b100000100 .
b101 +
#60000
b1111111111111111111111111111111110110010110000101000010001101011 $
b1111111111111111111111111111111110110010110000101000010001101011 3
b1111111111111111111111111111111110110010110000101000010001101011 7
b100000101 %
b100000101 /
b100000101 6
b1111111111111111111111111111111110110010110000101000010001101011 (
b1111111111111111111111111111111110110010110000101000010001101011 -
b1111111111111111111111111111111110110010110000101000010001101011 1
b100000101 )
b100000101 .
b110 +
#70000
b1111111111111111111111111111111110001001001101110101001000011001 $
b1111111111111111111111111111111110001001001101110101001000011001 3
b1111111111111111111111111111111110001001001101110101001000011001 7
b100000110 %
b100000110 /
b100000110 6
b1111111111111111111111111111111110001001001101110101001000011001 (
b1111111111111111111111111111111110001001001101110101001000011001 -
b1111111111111111111111111111111110001001001101110101001000011001 1
b100000110 )
b100000110 .
b111 +
#80000
b111100111110001100001001 $
b111100111110001100001001 3
b111100111110001100001001 7
b100000111 %
b100000111 /
b100000111 6
b111100111110001100001001 (
b111100111110001100001001 -
b111100111110001100001001 1
b100000111 )
b100000111 .
b1000 +
#90000
b110110101111100110100010110 $
b110110101111100110100010110 3
b110110101111100110100010110 7
b100001000 %
b100001000 /
b100001000 6
b110110101111100110100010110 (
b110110101111100110100010110 -
b110110101111100110100010110 1
b100001000 )
b100001000 .
b1001 +
#100000
b10010000101010011010100100100 "
b10010000101010011010100100100 8
b11111111 %
b11111111 /
b11111111 6
1#
0!
b11111111 )
b11111111 .
b101 '
b101 ,
b101 0
b101 4
b101 5
b0 +
#110000
b1111111111111111111111111111111111000000100010010101111010000010 "
b1111111111111111111111111111111111000000100010010101111010000010 8
b100000000 %
b100000000 /
b100000000 6
b100000000 )
b100000000 .
b1 +
#120000
b1111111111111111111111111111111110000100100001001101011000001011 "
b1111111111111111111111111111111110000100100001001101011000001011 8
b100000001 %
b100000001 /
b100000001 6
b100000001 )
b100000001 .
b10 +
#130000
b1111111111111111111111111111111110110001111100000101011001100110 "
b1111111111111111111111111111111110110001111100000101011001100110 8
b100000010 %
b100000010 /
b100000010 6
b100000010 )
b100000010 .
b11 +
#140000
b110101110010111101100010001 "
b110101110010111101100010001 8
b100000011 %
b100000011 /
b100000011 6
b100000011 )
b100000011 .
b100 +
#150000
b1000110110111111001100110010010 "
b1000110110111111001100110010010 8
b100000100 %
b100000100 /
b100000100 6
b100000100 )
b100000100 .
b101 +
#160000
b1111111111111111111111111111111110110010110000101000010001101011 "
b1111111111111111111111111111111110110010110000101000010001101011 8
b100000101 %
b100000101 /
b100000101 6
b100000101 )
b100000101 .
b110 +
#170000
b1111111111111111111111111111111110001001001101110101001000011001 "
b1111111111111111111111111111111110001001001101110101001000011001 8
b100000110 %
b100000110 /
b100000110 6
b100000110 )
b100000110 .
b111 +
#180000
b111100111110001100001001 "
b111100111110001100001001 8
b100000111 %
b100000111 /
b100000111 6
b100000111 )
b100000111 .
b1000 +
#190000
b110110101111100110100010110 "
b110110101111100110100010110 8
b100001000 %
b100001000 /
b100001000 6
b100001000 )
b100001000 .
b1001 +
#200000
b1010 +
