Assignment-1/AND/and_1bit.v

`timescale 1ns/1ps


module and_1bit(a, b, out);

input a ,b ;
output reg out;

always @(a or b ) begin
	
	if (a == 1'b1) begin
		if(b == 1'b1)
			out = 1'b1;

		else
			out = 1'b0;
	end
	else
		out = 1'b0;
end

endmodule

Assignment-1/AND/and_64bit.v
`timescale  1ns/1ps

module and_64bit(
	input signed [63:0]a,
	input signed [63:0]b,
	output signed [63:0] out
);

genvar i;

generate for(i = 0; i<64;i=i+1)
begin
	and_1bit g1(a[i],b[i],out[i]);
end
	
endgenerate

endmodule

Y86-64 Processor/And/and_64bittb.v
`timescale 1ns/1ps
`include "and_1bit.v"

module and_64bittb;

	reg signed [63:0]a;
	reg signed [63:0]b;

	wire signed [63:0]out;

	and_64bit dut(.a(a),.b(b),.out(out));

	initial begin
		$dumpfile("and_64bit.vcd");
		$dumpvars(0,and_64bittb);

		a=64'b0;
		b=64'b0;

	repeat(4) begin 
		#10 begin
			a = ~a;
			a = a<<1;
			a = ~a;
		end
		#20 begin
			b = ~b;
			b = b<<2;
			b = ~b;
		end
	end
		
	end

  initial 
		$monitor("a=%b b=%b\nout=%b \n\n",a,b,out);

endmodule

Y86-64 Processor/And/and_64bit.vcd
$date
	Wed Feb 02 02:43:35 2022
$end
$version
	Icarus Verilog
$end
$timescale
	1ps
$end
$scope module and_64bittb $end
$var wire 64 ! out [63:0] $end
$var reg 64 " a [63:0] $end
$var reg 64 # b [63:0] $end
$scope module dut $end
$var wire 64 $ a [63:0] $end
$var wire 64 % b [63:0] $end
$var wire 64 & out [63:0] $end
$scope begin genblk1[0] $end
$scope module g1 $end
$var wire 1 ' a $end
$var wire 1 ( b $end
$var reg 1 ) out $end
$upscope $end
$upscope $end
$scope begin genblk1[1] $end
$scope module g1 $end
$var wire 1 * a $end
$var wire 1 + b $end
$var reg 1 , out $end
$upscope $end
$upscope $end
$scope begin genblk1[2] $end
$scope module g1 $end
$var wire 1 - a $end
$var wire 1 . b $end
$var reg 1 / out $end
$upscope $end
$upscope $end
$scope begin genblk1[3] $end
$scope module g1 $end
$var wire 1 0 a $end
$var wire 1 1 b $end
$var reg 1 2 out $end
$upscope $end
$upscope $end
$scope begin genblk1[4] $end
$scope module g1 $end
$var wire 1 3 a $end
$var wire 1 4 b $end
$var reg 1 5 out $end
$upscope $end
$upscope $end
$scope begin genblk1[5] $end
$scope module g1 $end
$var wire 1 6 a $end
$var wire 1 7 b $end
$var reg 1 8 out $end
$upscope $end
$upscope $end
$scope begin genblk1[6] $end
$scope module g1 $end
$var wire 1 9 a $end
$var wire 1 : b $end
$var reg 1 ; out $end
$upscope $end
$upscope $end
$scope begin genblk1[7] $end
$scope module g1 $end
$var wire 1 < a $end
$var wire 1 = b $end
$var reg 1 > out $end
$upscope $end
$upscope $end
$scope begin genblk1[8] $end
$scope module g1 $end
$var wire 1 ? a $end
$var wire 1 @ b $end
$var reg 1 A out $end
$upscope $end
$upscope $end
$scope begin genblk1[9] $end
$scope module g1 $end
$var wire 1 B a $end
$var wire 1 C b $end
$var reg 1 D out $end
$upscope $end
$upscope $end
$scope begin genblk1[10] $end
$scope module g1 $end
$var wire 1 E a $end
$var wire 1 F b $end
$var reg 1 G out $end
$upscope $end
$upscope $end
$scope begin genblk1[11] $end
$scope module g1 $end
$var wire 1 H a $end
$var wire 1 I b $end
$var reg 1 J out $end
$upscope $end
$upscope $end
$scope begin genblk1[12] $end
$scope module g1 $end
$var wire 1 K a $end
$var wire 1 L b $end
$var reg 1 M out $end
$upscope $end
$upscope $end
$scope begin genblk1[13] $end
$scope module g1 $end
$var wire 1 N a $end
$var wire 1 O b $end
$var reg 1 P out $end
$upscope $end
$upscope $end
$scope begin genblk1[14] $end
$scope module g1 $end
$var wire 1 Q a $end
$var wire 1 R b $end
$var reg 1 S out $end
$upscope $end
$upscope $end
$scope begin genblk1[15] $end
$scope module g1 $end
$var wire 1 T a $end
$var wire 1 U b $end
$var reg 1 V out $end
$upscope $end
$upscope $end
$scope begin genblk1[16] $end
$scope module g1 $end
$var wire 1 W a $end
$var wire 1 X b $end
$var reg 1 Y out $end
$upscope $end
$upscope $end
$scope begin genblk1[17] $end
$scope module g1 $end
$var wire 1 Z a $end
$var wire 1 [ b $end
$var reg 1 \ out $end
$upscope $end
$upscope $end
$scope begin genblk1[18] $end
$scope module g1 $end
$var wire 1 ] a $end
$var wire 1 ^ b $end
$var reg 1 _ out $end
$upscope $end
$upscope $end
$scope begin genblk1[19] $end
$scope module g1 $end
$var wire 1 ` a $end
$var wire 1 a b $end
$var reg 1 b out $end
$upscope $end
$upscope $end
$scope begin genblk1[20] $end
$scope module g1 $end
$var wire 1 c a $end
$var wire 1 d b $end
$var reg 1 e out $end
$upscope $end
$upscope $end
$scope begin genblk1[21] $end
$scope module g1 $end
$var wire 1 f a $end
$var wire 1 g b $end
$var reg 1 h out $end
$upscope $end
$upscope $end
$scope begin genblk1[22] $end
$scope module g1 $end
$var wire 1 i a $end
$var wire 1 j b $end
$var reg 1 k out $end
$upscope $end
$upscope $end
$scope begin genblk1[23] $end
$scope module g1 $end
$var wire 1 l a $end
$var wire 1 m b $end
$var reg 1 n out $end
$upscope $end
$upscope $end
$scope begin genblk1[24] $end
$scope module g1 $end
$var wire 1 o a $end
$var wire 1 p b $end
$var reg 1 q out $end
$upscope $end
$upscope $end
$scope begin genblk1[25] $end
$scope module g1 $end
$var wire 1 r a $end
$var wire 1 s b $end
$var reg 1 t out $end
$upscope $end
$upscope $end
$scope begin genblk1[26] $end
$scope module g1 $end
$var wire 1 u a $end
$var wire 1 v b $end
$var reg 1 w out $end
$upscope $end
$upscope $end
$scope begin genblk1[27] $end
$scope module g1 $end
$var wire 1 x a $end
$var wire 1 y b $end
$var reg 1 z out $end
$upscope $end
$upscope $end
$scope begin genblk1[28] $end
$scope module g1 $end
$var wire 1 { a $end
$var wire 1 | b $end
$var reg 1 } out $end
$upscope $end
$upscope $end
$scope begin genblk1[29] $end
$scope module g1 $end
$var wire 1 ~ a $end
$var wire 1 !" b $end
$var reg 1 "" out $end
$upscope $end
$upscope $end
$scope begin genblk1[30] $end
$scope module g1 $end
$var wire 1 #" a $end
$var wire 1 $" b $end
$var reg 1 %" out $end
$upscope $end
$upscope $end
$scope begin genblk1[31] $end
$scope module g1 $end
$var wire 1 &" a $end
$var wire 1 '" b $end
$var reg 1 (" out $end
$upscope $end
$upscope $end
$scope begin genblk1[32] $end
$scope module g1 $end
$var wire 1 )" a $end
$var wire 1 *" b $end
$var reg 1 +" out $end
$upscope $end
$upscope $end
$scope begin genblk1[33] $end
$scope module g1 $end
$var wire 1 ," a $end
$var wire 1 -" b $end
$var reg 1 ." out $end
$upscope $end
$upscope $end
$scope begin genblk1[34] $end
$scope module g1 $end
$var wire 1 /" a $end
$var wire 1 0" b $end
$var reg 1 1" out $end
$upscope $end
$upscope $end
$scope begin genblk1[35] $end
$scope module g1 $end
$var wire 1 2" a $end
$var wire 1 3" b $end
$var reg 1 4" out $end
$upscope $end
$upscope $end
$scope begin genblk1[36] $end
$scope module g1 $end
$var wire 1 5" a $end
$var wire 1 6" b $end
$var reg 1 7" out $end
$upscope $end
$upscope $end
$scope begin genblk1[37] $end
$scope module g1 $end
$var wire 1 8" a $end
$var wire 1 9" b $end
$var reg 1 :" out $end
$upscope $end
$upscope $end
$scope begin genblk1[38] $end
$scope module g1 $end
$var wire 1 ;" a $end
$var wire 1 <" b $end
$var reg 1 =" out $end
$upscope $end
$upscope $end
$scope begin genblk1[39] $end
$scope module g1 $end
$var wire 1 >" a $end
$var wire 1 ?" b $end
$var reg 1 @" out $end
$upscope $end
$upscope $end
$scope begin genblk1[40] $end
$scope module g1 $end
$var wire 1 A" a $end
$var wire 1 B" b $end
$var reg 1 C" out $end
$upscope $end
$upscope $end
$scope begin genblk1[41] $end
$scope module g1 $end
$var wire 1 D" a $end
$var wire 1 E" b $end
$var reg 1 F" out $end
$upscope $end
$upscope $end
$scope begin genblk1[42] $end
$scope module g1 $end
$var wire 1 G" a $end
$var wire 1 H" b $end
$var reg 1 I" out $end
$upscope $end
$upscope $end
$scope begin genblk1[43] $end
$scope module g1 $end
$var wire 1 J" a $end
$var wire 1 K" b $end
$var reg 1 L" out $end
$upscope $end
$upscope $end
$scope begin genblk1[44] $end
$scope module g1 $end
$var wire 1 M" a $end
$var wire 1 N" b $end
$var reg 1 O" out $end
$upscope $end
$upscope $end
$scope begin genblk1[45] $end
$scope module g1 $end
$var wire 1 P" a $end
$var wire 1 Q" b $end
$var reg 1 R" out $end
$upscope $end
$upscope $end
$scope begin genblk1[46] $end
$scope module g1 $end
$var wire 1 S" a $end
$var wire 1 T" b $end
$var reg 1 U" out $end
$upscope $end
$upscope $end
$scope begin genblk1[47] $end
$scope module g1 $end
$var wire 1 V" a $end
$var wire 1 W" b $end
$var reg 1 X" out $end
$upscope $end
$upscope $end
$scope begin genblk1[48] $end
$scope module g1 $end
$var wire 1 Y" a $end
$var wire 1 Z" b $end
$var reg 1 [" out $end
$upscope $end
$upscope $end
$scope begin genblk1[49] $end
$scope module g1 $end
$var wire 1 \" a $end
$var wire 1 ]" b $end
$var reg 1 ^" out $end
$upscope $end
$upscope $end
$scope begin genblk1[50] $end
$scope module g1 $end
$var wire 1 _" a $end
$var wire 1 `" b $end
$var reg 1 a" out $end
$upscope $end
$upscope $end
$scope begin genblk1[51] $end
$scope module g1 $end
$var wire 1 b" a $end
$var wire 1 c" b $end
$var reg 1 d" out $end
$upscope $end
$upscope $end
$scope begin genblk1[52] $end
$scope module g1 $end
$var wire 1 e" a $end
$var wire 1 f" b $end
$var reg 1 g" out $end
$upscope $end
$upscope $end
$scope begin genblk1[53] $end
$scope module g1 $end
$var wire 1 h" a $end
$var wire 1 i" b $end
$var reg 1 j" out $end
$upscope $end
$upscope $end
$scope begin genblk1[54] $end
$scope module g1 $end
$var wire 1 k" a $end
$var wire 1 l" b $end
$var reg 1 m" out $end
$upscope $end
$upscope $end
$scope begin genblk1[55] $end
$scope module g1 $end
$var wire 1 n" a $end
$var wire 1 o" b $end
$var reg 1 p" out $end
$upscope $end
$upscope $end
$scope begin genblk1[56] $end
$scope module g1 $end
$var wire 1 q" a $end
$var wire 1 r" b $end
$var reg 1 s" out $end
$upscope $end
$upscope $end
$scope begin genblk1[57] $end
$scope module g1 $end
$var wire 1 t" a $end
$var wire 1 u" b $end
$var reg 1 v" out $end
$upscope $end
$upscope $end
$scope begin genblk1[58] $end
$scope module g1 $end
$var wire 1 w" a $end
$var wire 1 x" b $end
$var reg 1 y" out $end
$upscope $end
$upscope $end
$scope begin genblk1[59] $end
$scope module g1 $end
$var wire 1 z" a $end
$var wire 1 {" b $end
$var reg 1 |" out $end
$upscope $end
$upscope $end
$scope begin genblk1[60] $end
$scope module g1 $end
$var wire 1 }" a $end
$var wire 1 ~" b $end
$var reg 1 !# out $end
$upscope $end
$upscope $end
$scope begin genblk1[61] $end
$scope module g1 $end
$var wire 1 "# a $end
$var wire 1 ## b $end
$var reg 1 $# out $end
$upscope $end
$upscope $end
$scope begin genblk1[62] $end
$scope module g1 $end
$var wire 1 %# a $end
$var wire 1 &# b $end
$var reg 1 '# out $end
$upscope $end
$upscope $end
$scope begin genblk1[63] $end
$scope module g1 $end
$var wire 1 (# a $end
$var wire 1 )# b $end
$var reg 1 *# out $end
$upscope $end
$upscope $end
$upscope $end
$upscope $end
$enddefinitions $end
#0
$dumpvars
0*#
0)#
0(#
0'#
0&#
0%#
0$#
0##
0"#
0!#
0~"
0}"
0|"
0{"
0z"
0y"
0x"
0w"
0v"
0u"
0t"
0s"
0r"
0q"
0p"
0o"
0n"
0m"
0l"
0k"
0j"
0i"
0h"
0g"
0f"
0e"
0d"
0c"
0b"
0a"
0`"
0_"
0^"
0]"
0\"
0["
0Z"
0Y"
0X"
0W"
0V"
0U"
0T"
0S"
0R"
0Q"
0P"
0O"
0N"
0M"
0L"
0K"
0J"
0I"
0H"
0G"
0F"
0E"
0D"
0C"
0B"
0A"
0@"
0?"
0>"
0="
0<"
0;"
0:"
09"
08"
07"
06"
05"
04"
03"
02"
01"
00"
0/"
0."
0-"
0,"
0+"
0*"
0)"
0("
0'"
0&"
0%"
0$"
0#"
0""
0!"
0~
0}
0|
0{
0z
0y
0x
0w
0v
0u
0t
0s
0r
0q
0p
0o
0n
0m
0l
0k
0j
0i
0h
0g
0f
0e
0d
0c
0b
0a
0`
0_
0^
0]
0\
0[
0Z
0Y
0X
0W
0V
0U
0T
0S
0R
0Q
0P
0O
0N
0M
0L
0K
0J
0I
0H
0G
0F
0E
0D
0C
0B
0A
0@
0?
0>
0=
0<
0;
0:
09
08
07
06
05
04
03
02
01
00
0/
0.
0-
0,
0+
0*
0)
0(
0'
b0 &
b0 %
b0 $
b0 #
b0 "
b0 !
$end
#10000
1'
b1 "
b1 $
#30000
b1 !
b1 &
1)
1(
1+
b11 #
b11 %
#40000
b11 !
b11 &
1,
1*
b11 "
b11 $
#60000
1.
11
b1111 #
b1111 %
#70000
b111 !
b111 &
1/
1-
b111 "
b111 $
#90000
14
17
b111111 #
b111111 %
#100000
b1111 !
b1111 &
12
10
b1111 "
b1111 $
#120000
1:
1=
b11111111 #
b11111111 %
