Assignment-1/AND/and_1bit.v

`timescale 1ns/1ps


module and_1bit(a, b, out);

input a ,b ;
output reg out;

always @(a or b ) begin
	
	if (a == 1'b1) begin
		if(b == 1'b1)
			out = 1'b1;

		else
			out = 1'b0;
	end
	else
		out = 1'b0;
end

endmodule

Y86-64 Processor/seq/Execute/And/and_1bittb.v
`timescale 1ns/1ps


module and_1bittb;

	reg a,b;
	wire out;




	and_1bit dut(.a(a),.b(b),.out(out));

	initial begin
		$dumpfile("and_1bit.vcd");
		$dumpvars(0,and_1bittb);

		a=1'b0;
		b=1'b0;
	repeat(4) begin 
		#10 a = ~a;
		#20 b = ~b;
	end
		
	end


	
		
	
	
  initial 
		$monitor("a=%b b=%b out=%b \n",a,b,out);

endmodule

Y86-64 Processor/seq/Execute/And/and_1bit.vcd
$date
	Sat Jan 29 01:07:10 2022
$end
$version
	Icarus Verilog
$end
$timescale
	1ps
$end
$scope module and_1bittb $end
$var wire 1 ! out $end
$var reg 1 " a $end
$var reg 1 # b $end
$scope module dut $end
$var wire 1 " a $end
$var wire 1 # b $end
$var reg 1 ! out $end
$upscope $end
$upscope $end
$enddefinitions $end
#0
$dumpvars
0#
0"
0!
$end
#10000
1"
#30000
1!
1#
#40000
0!
0"
#60000
0#
#70000
1"
#90000
1!
1#
#100000
0!
0"
#120000
0#
